birdbrain/__init__.py
birdbrain/atlas.py
birdbrain/downloading.py
birdbrain/utils.py
birdbrain/data/__init__.py
birdbrain/data/make_dataset.py
birdbrain/features/__init__.py
birdbrain/features/build_features.py
birdbrain/models/__init__.py
birdbrain/models/predict_model.py
birdbrain/models/train_model.py
birdbrain/visualization/__init__.py
birdbrain/visualization/plotting_2d.py
birdbrain/visualization/plotting_3d.py
birdbrain/visualization/visualize.py
birdbrain-0.1.3.dist-info/LICENSE
birdbrain-0.1.3.dist-info/METADATA
birdbrain-0.1.3.dist-info/WHEEL
birdbrain-0.1.3.dist-info/top_level.txt
birdbrain-0.1.3.dist-info/RECORD
