Metadata-Version: 2.1
Name: birdbrain
Version: 0.1.3
Summary: Tools for using the songbird brain atlas
Home-page: https://github.com/timsainb/birdbrain
Author: Tim Sainburg
License: BSD-3
Platform: UNKNOWN
Classifier: Programming Language :: Python :: 3
Classifier: License :: OSI Approved :: BSD License
Classifier: Operating System :: OS Independent
Classifier: Framework :: IPython
Classifier: Intended Audience :: Science/Research
Classifier: Topic :: Education
Classifier: Topic :: Multimedia :: Graphics
Classifier: Topic :: Scientific/Engineering :: Visualization
Requires-Dist: ipywidgets (>=7.0.1)
Requires-Dist: ipydatawidgets
Requires-Dist: traittypes
Requires-Dist: traitlets
Requires-Dist: numpy (>=1.11.0)
Requires-Dist: k3d
Requires-Dist: nibabel
Requires-Dist: nipy
Requires-Dist: scipy
Requires-Dist: matplotlib
Requires-Dist: vtk
Requires-Dist: pandas
Requires-Dist: scikit-image
Requires-Dist: tqdm
Requires-Dist: patool
